tgio/__init__.py
tgio/_files.py
tgio/_keyboard.py
tgio/main.py
tgio-0.17.dist-info/licenses/LICENSE
tgio-0.17.dist-info/METADATA
tgio-0.17.dist-info/WHEEL
tgio-0.17.dist-info/top_level.txt
tgio-0.17.dist-info/RECORD
