Metadata-Version: 2.4
Name: tgio
Version: 0.17
Summary: The simplest library for Telegram bots
Home-page: https://github.com/kosyachniy/tgio
Author: Alex Poloz
Author-email: Alex Poloz <alexypoloz@gmail.com>
License: MIT License
Project-URL: Source, https://github.com/kosyachniy/tgio
Keywords: simple,Telegram,bot
Classifier: Development Status :: 4 - Beta
Classifier: Environment :: Console
Classifier: Intended Audience :: Developers
Classifier: Topic :: Software Development :: Libraries :: Application Frameworks
Classifier: License :: OSI Approved :: MIT License
Classifier: Programming Language :: Python :: 3
Classifier: Programming Language :: Python :: 3.9
Classifier: Programming Language :: Python :: 3.10
Classifier: Programming Language :: Python :: 3.11
Classifier: Programming Language :: Python :: 3.12
Classifier: Programming Language :: Python :: 3.13
Classifier: Operating System :: OS Independent
Requires-Python: >=3.9, <4
License-File: LICENSE
Requires-Dist: aiogram>=3.23.0
Provides-Extra: dev
Requires-Dist: twine==6.2.0; extra == "dev"
Requires-Dist: setuptools==80.9.0; extra == "dev"
Requires-Dist: pylint==3.3.9; extra == "dev"
Requires-Dist: pytest==8.4.2; extra == "dev"
Requires-Dist: pytest-asyncio==1.2.0; extra == "dev"
Requires-Dist: build>=1.2.1; extra == "dev"
Dynamic: author
Dynamic: home-page
Dynamic: license-file
Dynamic: requires-python
